setup.py
ircbot/__init__.py
ircbot/main.py
ircbot.egg-info/PKG-INFO
ircbot.egg-info/SOURCES.txt
ircbot.egg-info/dependency_links.txt
ircbot.egg-info/entry_points.txt
ircbot.egg-info/requires.txt
ircbot.egg-info/top_level.txt