Metadata-Version: 1.0
Name: ircbot
Version: 0.1dev
Summary: a rather simple echo irc bot to stand as a simple example of how this could be done.
Home-page: https://bitbucket.org/smcquay/ircbot
Author: Stephen McQuay
Author-email: stephen@mcquay.me
License: WTFPL
Platform: UNKNOWN
